[
    {
        "app_id": "io.snapcraft.ultimate-media-downloader2-F5uXTlPiCvo1tDoqtuhPJJGsF6QOReal",
        "date_created": 1583764362.0,
        "description": "no se debe instalar",
        "distro": "CentOS Linux",
        "karma_down": 0,
        "karma_up": 0,
        "locale": "es_CR",
        "rating": 40,
        "reported": 0,
        "review_id": 162052,
        "score": 0,
        "summary": "no le tengo confianza",
        "user_display": "josecasba",
        "user_hash": "363ab7a647239e893a708c6c653f99a49227c652",
        "user_skey": "6f2e5523d52f28bdb4d0bf1fb32effddd7b6c108",
        "version": "1"
    },
    {
        "app_id": "io.snapcraft.ultimate-media-downloader2-F5uXTlPiCvo1tDoqtuhPJJGsF6QOReal",
        "date_created": 1588435549.0,
        "description": "una basura no te deja ni probar la aplicacion",
        "distro": "Debian GNU/Linux",
        "karma_down": 0,
        "karma_up": 0,
        "locale": "es_AR",
        "rating": 20,
        "reported": 0,
        "review_id": 198693,
        "score": 0,
        "summary": "hay que pagar",
        "user_display": "DANNY",
        "user_hash": "257b867a32ea6835936470a6d63409b071ba22ee",
        "user_skey": "6f2e5523d52f28bdb4d0bf1fb32effddd7b6c108",
        "version": "1"
    },
    {
        "app_id": "io.snapcraft.ultimate-media-downloader2-F5uXTlPiCvo1tDoqtuhPJJGsF6QOReal",
        "date_created": 1598992632.0,
        "description": "No permite hacer una prueba, de una vez pide comprarla ....",
        "distro": "Ubuntu",
        "karma_down": 0,
        "karma_up": 0,
        "locale": "es_ES",
        "rating": 20,
        "reported": 0,
        "review_id": 266143,
        "score": 0,
        "summary": "La detesto",
        "user_display": "julio",
        "user_hash": "e7c981a92a39b2df2153056d72faadda9f97c35c",
        "user_skey": "6f2e5523d52f28bdb4d0bf1fb32effddd7b6c108",
        "version": "1"
    },
    {
        "app_id": "io.snapcraft.ultimate-media-downloader2-F5uXTlPiCvo1tDoqtuhPJJGsF6QOReal",
        "date_created": 1606860490.0,
        "description": "ni habre el programa y quiere que le compre...HORRIBLE!",
        "distro": "Zorin OS",
        "karma_down": 0,
        "karma_up": 0,
        "locale": "es_ES",
        "rating": 20,
        "reported": 0,
        "review_id": 311310,
        "score": 0,
        "summary": "HORRIBLE!",
        "user_display": "JORGE ALBERTO",
        "user_hash": "138bb4b1805172859f4020fafa3f4970887c1ee2",
        "user_skey": "6f2e5523d52f28bdb4d0bf1fb32effddd7b6c108",
        "version": "1"
    }
]