[
    {
        "app_id": "lyx.desktop",
        "date_created": 1509158866.0,
        "description": "Es uno de los programas que m\u00e1s uso. Es mucho m\u00e1s potente que LibreOffice Writer, y los resultados son preciosos. Vale la pena el tiempo invertido en aprender a manejarlo.",
        "distro": "Debian GNU/Linux",
        "karma_down": 0,
        "karma_up": 7,
        "locale": "es_CO",
        "rating": 100,
        "reported": 0,
        "review_id": 5165,
        "score": 14,
        "summary": "Lo recomiendo 100%",
        "user_display": "henry",
        "user_hash": "55bc6572009df3e0d75dadc595be7735479ee6bd",
        "user_skey": "51a49744ab7fe0d9ebe3fb13dfda098dfe26f512",
        "version": "2.2.2"
    },
    {
        "app_id": "lyx.desktop",
        "date_created": 1522241130.0,
        "description": "Buena aplicaci\u00f3n para textos cient\u00edficos, los presenta de forma elegante, y ayuda mucho en la composici\u00f3n de texto. Un poco dif\u00edcil de manejar, pero vale la pena el esfuerzo. Tiene incorporado sus propios manuales.",
        "distro": "Debian GNU/Linux",
        "karma_down": 0,
        "karma_up": 7,
        "locale": "es_EC",
        "rating": 100,
        "reported": 0,
        "review_id": 6976,
        "score": 14,
        "summary": "Aplicacion para textos cient\u00edficos",
        "user_display": "Hernan Felipe Gudi\u00f1o Sono",
        "user_hash": "c093f20cf7d19dfa6b81c90751dd826226d912d7",
        "user_skey": "51a49744ab7fe0d9ebe3fb13dfda098dfe26f512",
        "version": "2.2.2"
    },
    {
        "app_id": "lyx.desktop",
        "date_created": 1556230493.0,
        "description": "Fant\u00e1sticos documentos de calidad profesional.",
        "distro": "Fedora",
        "karma_down": 0,
        "karma_up": 0,
        "locale": "es_ES",
        "rating": 100,
        "reported": 0,
        "review_id": 25397,
        "score": 0,
        "summary": "Recomendada 100%",
        "user_display": "kk",
        "user_hash": "3261f402014758cd35e9c5fb191e6e08696cb6c5",
        "user_skey": "51a49744ab7fe0d9ebe3fb13dfda098dfe26f512",
        "version": "2.3.2"
    },
    {
        "app_id": "lyx.desktop",
        "date_created": 1588887917.0,
        "description": "El mejor procesador que existe, es increible la calidad de documentos que podemos hacer.",
        "distro": "Ubuntu",
        "karma_down": 0,
        "karma_up": 0,
        "locale": "es_MX.UTF-8",
        "rating": 100,
        "reported": 0,
        "review_id": 203427,
        "score": 0,
        "summary": "Una maravilla",
        "user_display": "casa",
        "user_hash": "055447705b971d5d684ab6ed7c8295169c195dac",
        "user_skey": "51a49744ab7fe0d9ebe3fb13dfda098dfe26f512",
        "version": "2.3.4.2"
    },
    {
        "app_id": "lyx.desktop",
        "date_created": 1592062790.0,
        "description": "En la p\u00e1gina web del proyecto se indica claramente que la licencia de este software es libre.",
        "distro": "Ubuntu",
        "karma_down": 0,
        "karma_up": 0,
        "locale": "es_ES.UTF-8",
        "rating": 100,
        "reported": 0,
        "review_id": 229861,
        "score": 0,
        "summary": "\u00bfPor qu\u00e9 la licencia indica que es propietaria?",
        "user_display": "Juan",
        "user_hash": "559d8d7637f81f52b32c4341442278dbfb1a6007",
        "user_skey": "51a49744ab7fe0d9ebe3fb13dfda098dfe26f512",
        "version": "2.3.4.2"
    }
]